ingysec/__init__.py
ingysec/bandit.yaml
ingysec/custom_rules.yml
ingysec/ingy.py
ingysec/initialization.py
ingysec/shell_escape_finder.py
ingysec/utils.py
ingysec-0.5.0.dist-info/METADATA
ingysec-0.5.0.dist-info/WHEEL
ingysec-0.5.0.dist-info/entry_points.txt
ingysec-0.5.0.dist-info/RECORD
