Metadata-Version: 2.1
Name: ingysec
Version: 0.5.0
Summary: 
Author: briskdust
Author-email: briskdust@gmail.com
Requires-Python: >=3.12,<4.0
Classifier: Programming Language :: Python :: 3
Classifier: Programming Language :: Python :: 3.12
Requires-Dist: bandit (>=1.7.8,<2.0.0)
Requires-Dist: boofuzz (>=0.4.2,<0.5.0)
Requires-Dist: flask (>=3.0.3,<4.0.0)
Requires-Dist: flask-cors (>=4.0.0,<5.0.0)
Requires-Dist: jira (>=3.8.0,<4.0.0)
Requires-Dist: requests (>=2.31.0,<3.0.0)
Requires-Dist: requests-toolbelt (>=1.0.0,<2.0.0)
Requires-Dist: rich (>=13.7.1,<14.0.0)
Requires-Dist: semgrep (>=1.75.0,<2.0.0)
Requires-Dist: tabulate (>=0.9.0,<0.10.0)
